finsenti/__init__.py
finsenti/aggregation.py
finsenti/collection.py
finsenti/main.py
finsenti/pipeline.py
finsenti/preprocessing.py
finsenti/sentiment.py
finsenti-0.1.0.dist-info/METADATA
finsenti-0.1.0.dist-info/WHEEL
finsenti-0.1.0.dist-info/top_level.txt
finsenti-0.1.0.dist-info/RECORD
