Metadata-Version: 2.4
Name: finsenti
Version: 0.1.0
Summary: A package for financial sentiment analysis using news articles.
Home-page: https://github.com/vaibhavjha100/Sentiment-Analysis
Author: Vaibhav Jha
Author-email: vaibhavjha100@gmail.com
License: MIT
Classifier: Programming Language :: Python :: 3
Classifier: License :: OSI Approved :: MIT License
Classifier: Operating System :: OS Independent
Classifier: Topic :: Software Development :: Libraries
Classifier: Intended Audience :: Financial and Insurance Industry
Requires-Python: >=3.7
Requires-Dist: pandas
Requires-Dist: marketminer
Requires-Dist: google-genai
Requires-Dist: python-dotenv
Requires-Dist: transformers
Requires-Dist: torch
Requires-Dist: hf_xet
Requires-Dist: scipy
Dynamic: author
Dynamic: author-email
Dynamic: classifier
Dynamic: description
Dynamic: description-content-type
Dynamic: home-page
Dynamic: license
Dynamic: requires-dist
Dynamic: requires-python
Dynamic: summary
